layersfusion/__init__.py
layersfusion/layers/__init__.py
layersfusion/layers/operations.py
layersfusion/utils/__init__.py
layersfusion/utils/shared_operations.py
layersfusion-0.0.1.dist-info/METADATA
layersfusion-0.0.1.dist-info/WHEEL
layersfusion-0.0.1.dist-info/top_level.txt
layersfusion-0.0.1.dist-info/RECORD
